{"enabled_wallets":[{"token_query_id":"bitcoin|derived:bip84","decimals":8,"coin_name":"Bitcoin","coin_code":"BTC"},{"decimals":18,"coin_name":"Ethereum","coin_code":"ETH","token_query_id":"ethereum|native"},{"token_query_id":"binance-smart-chain|native","decimals":18,"coin_code":"BNB","coin_name":"Binance Coin"},{"decimals":6,"token_query_id":"ethereum|eip20:0xdac17f958d2ee523a2206206994597c13d831ec7","coin_code":"USDT","coin_name":"Tether"},{"token_query_id":"binance-smart-chain|eip20:0xe9e7cea3dedca5984780bafc599bd69add087d56","coin_name":"Binance USD","coin_code":"BUSD","decimals":18},{"coin_name":"Tether","decimals":18,"token_query_id":"binance-smart-chain|eip20:0x55d398326f99059ff775485246999027b3197955","coin_code":"USDT"},{"coin_name":"Tether","decimals":6,"token_query_id":"tron|eip20:TR7NHqjeKQxGTCi8q8ZY4pL8otSzgjLj6t","coin_code":"USDT"},{"coin_code":"USDT","coin_name":"Tether","token_query_id":"the-open-network|the-open-network:EQCxE6mUtQJKFnGfaROTKOt1lZbDiiX1kCixRv7Nw2Id_sDs","decimals":6},{"coin_code":"USDT","decimals":6,"token_query_id":"polygon-pos|eip20:0xc2132d05d31c914a87c6611c10748aeb04b58e8f","coin_name":"Tether"},{"token_query_id":"avalanche|eip20:0x9702230a8ea53601f5cd2dc00fdbc13d4df4a8c7","decimals":6,"coin_code":"USDT","coin_name":"Tether"},{"token_query_id":"fantom|eip20:0x049d68029688eabf473097a2fc38ef61633a3c7a","coin_code":"USDT","coin_name":"Tether","decimals":6},{"coin_code":"USDT","coin_name":"Tether","decimals":6,"token_query_id":"arbitrum-one|eip20:0xfd086bc7cd5c481dcc9c85ebe478a1c0b69fcbb9"},{"coin_name":"Tether","token_query_id":"optimistic-ethereum|eip20:0x94b008aa00579c1307b0ef2c499ad98a8ce58e58","decimals":6,"coin_code":"USDT"},{"coin_code":"WETH","coin_name":"L2 Standard Bridged WETH (Base)","decimals":18,"token_query_id":"base|eip20:0x4200000000000000000000000000000000000006"},{"coin_code":"TRX","decimals":6,"token_query_id":"tron|native","coin_name":"TRON"},{"token_query_id":"the-open-network|native","coin_code":"TONCOIN","decimals":9,"coin_name":"The Open Network"},{"decimals":18,"token_query_id":"polygon-pos|native","coin_name":"Polygon","coin_code":"POL"},{"coin_code":"ETH","coin_name":"Ethereum","token_query_id":"base|native","decimals":18},{"coin_code":"AVAX","decimals":18,"coin_name":"Avalanche","token_query_id":"avalanche|native"},{"decimals":8,"token_query_id":"zcash|native","coin_code":"ZEC","settings":{"birthday_height":"2717500"},"coin_name":"Zcash"},{"coin_name":"eCash","decimals":2,"token_query_id":"ecash|native","coin_code":"XEC"},{"coin_name":"Bitcoin Cash","decimals":8,"token_query_id":"bitcoin-cash|address_type:type145","coin_code":"BCH"},{"coin_name":"Litecoin","token_query_id":"litecoin|derived:bip84","coin_code":"LTC","decimals":8},{"coin_name":"Dash","token_query_id":"dash|native","decimals":8,"coin_code":"DASH"},{"coin_code":"BNB","decimals":18,"token_query_id":"binancecoin|native","coin_name":"Binance Coin"},{"coin_code":"XDAI","decimals":18,"token_query_id":"gnosis|native","coin_name":"xDAI"},{"coin_code":"FTM","coin_name":"Fantom","decimals":18,"token_query_id":"fantom|native"},{"token_query_id":"arbitrum-one|native","coin_code":"ETH","coin_name":"Ethereum","decimals":18},{"coin_code":"ETH","token_query_id":"optimistic-ethereum|native","coin_name":"Ethereum","decimals":18}],"crypto":{"kdf":"scrypt","mac":"c84a17f6bed4e40c8b593221416d32a83f97d0e5de35dac834097429cc39c294","kdfparams":{"n":16384,"p":4,"salt":"unstoppable","dklen":32,"r":8},"cipherparams":{"iv":"39b2e0c6b950d601400ce90e031fea1f"},"ciphertext":"e\/SQ+w2m95s6ySF8Gyvxl360vi2XFJDm0QFJJqyO64ox1vFq\/tCqdUVs9Xq1zy+\/FOlnmfV6yRQ95d8lILCZVfdfMErXCfD68Cgpuqhj","cipher":"aes-128-ctr"},"manual_backup":false,"version":2,"type":"mnemonic","id":"6641f58d70aa984e083a988ae89e0a6eb9ea7c1fe0f23dc456a7acfeec6af1879438efa7a29cdca03ca35afed4a61c47e389b3131d04194fa2c6e45f08849b15","timestamp":1740558416,"file_backup":false}